matplotlibaux/__init__.py
matplotlibaux/matplotlibaux.py
matplotlibaux-20.2.23.0.dist-info/LICENSE
matplotlibaux-20.2.23.0.dist-info/METADATA
matplotlibaux-20.2.23.0.dist-info/WHEEL
matplotlibaux-20.2.23.0.dist-info/top_level.txt
matplotlibaux-20.2.23.0.dist-info/RECORD
