Metadata-Version: 2.1
Name: matplotlibaux
Version: 20.2.23.0
Summary: matplotlib auxiliary stuff
Home-page: https://github.com/trevisanj/matplotlibaux
Author: Julio Trevisan
Author-email: juliotrevisan@gmail.com
License: GNU GPLv3
Keywords: matplotlib
Platform: any
